{
  "ingredients": [
    {
      "title": "Cébette - Ciboule - Cive - Oignon vert"
    },
    {
      "title": "Chou vert",
      "saisons": [
        "automne",
        "hiver"
      ],
      "pFrais": true
    },
    {
      "title": "Figues Sèches",
      "pFrais": true
    },
    {
      "title": "Abricot",
      "pFrais": true
    },
    {
      "title": "Ail",
      "pFrais": true
    },
    {
      "title": "Airelle",
      "pFrais": true
    },
    {
      "title": "Ananas",
      "pFrais": true
    },
    {
      "title": "Ananas (conserve)",
      "pFrais": false
    },
    {
      "title": "Artichaut",
      "pFrais": true
    },
    {
      "title": "Asperge blanche",
      "pFrais": true
    },
    {
      "title": "Asperge verte",
      "pFrais": true
    },
    {
      "title": "Aubergine",
      "pFrais": true
    },
    {
      "title": "Avocat",
      "pFrais": true
    },
    {
      "title": "Banane",
      "pFrais": true
    },
    {
      "title": "Banane séchée",
      "pFrais": false
    },
    {
      "title": "Bette (blette)",
      "pFrais": true
    },
    {
      "title": "Betterave rouge",
      "pFrais": true
    },
    {
      "title": "Brocoli",
      "pFrais": true
    },
    {
      "title": "Canneberge",
      "pFrais": true
    },
    {
      "title": "Carotte",
      "pFrais": true
    },
    {
      "title": "Cassis",
      "pFrais": true
    },
    {
      "title": "Catalonia",
      "pFrais": true
    },
    {
      "title": "Céleri",
      "alergenesIng": [
        "Céleri"
      ],
      "pFrais": true
    },
    {
      "title": "Céleri branche",
      "alergenesIng": [
        "Céleri"
      ],
      "pFrais": true
    },
    {
      "title": "Céleri rave",
      "alergenesIng": [
        "Céleri"
      ],
      "pFrais": true
    },
    {
      "title": "Cerise",
      "pFrais": true
    },
    {
      "title": "Cerise aux sirop",
      "pFrais": false
    },
    {
      "title": "Cerises Griottes",
      "pFrais": true
    },
    {
      "title": "Champignon noir",
      "pFrais": true
    },
    {
      "title": "Champignons",
      "pFrais": true
    },
    {
      "title": "Champignons (conserve)",
      "pFrais": false
    },
    {
      "title": "Chou blanc",
      "pFrais": true
    },
    {
      "title": "Chou de Bruxelles",
      "pFrais": true
    },
    {
      "title": "Chou frisé",
      "pFrais": true
    },
    {
      "title": "Chou Romanesco",
      "pFrais": true
    },
    {
      "title": "Chou rouge",
      "pFrais": true
    },
    {
      "title": "Chou-chinois",
      "pFrais": true
    },
    {
      "title": "Chou-fleur",
      "pFrais": true
    },
    {
      "title": "Chou-rave",
      "pFrais": true
    },
    {
      "title": "Cima di Rapa",
      "pFrais": true
    },
    {
      "title": "Citron jaune",
      "pFrais": true
    },
    {
      "title": "Citron confit",
      "pFrais": false
    },
    {
      "title": "Citron vert",
      "pFrais": true
    },
    {
      "title": "Citrouille",
      "pFrais": true
    },
    {
      "title": "Clémentine",
      "pFrais": true
    },
    {
      "title": "Coing",
      "pFrais": true
    },
    {
      "title": "Concombre",
      "pFrais": true
    },
    {
      "title": "Courge",
      "pFrais": true
    },
    {
      "title": "Courge Butternut",
      "pFrais": true
    },
    {
      "title": "Courgette",
      "pFrais": true
    },
    {
      "title": "Datte",
      "pFrais": true
    },
    {
      "title": "Echalote",
      "pFrais": true
    },
    {
      "title": "Endive",
      "pFrais": true
    },
    {
      "title": "Epinard",
      "pFrais": true
    },
    {
      "title": "Fenouil",
      "pFrais": true
    },
    {
      "title": "Figue",
      "pFrais": true
    },
    {
      "title": "Fraise",
      "pFrais": true
    },
    {
      "title": "Fraise des bois",
      "pFrais": true
    },
    {
      "title": "Framboise",
      "pFrais": true
    },
    {
      "title": "Fruit de la passion",
      "pFrais": true
    },
    {
      "title": "Grenade",
      "pFrais": true
    },
    {
      "title": "Groseille",
      "pFrais": true
    },
    {
      "title": "Harcitos beurre",
      "pFrais": true
    },
    {
      "title": "Haricots plats",
      "pFrais": true
    },
    {
      "title": "Haricots verts",
      "pFrais": true
    },
    {
      "title": "Kaki",
      "pFrais": true
    },
    {
      "title": "Kiwi",
      "pFrais": true
    },
    {
      "title": "Kumquat",
      "pFrais": true
    },
    {
      "title": "Laitue romaine",
      "pFrais": true
    },
    {
      "title": "Litchi",
      "pFrais": true
    },
    {
      "title": "Mandarine",
      "pFrais": true
    },
    {
      "title": "Mangue",
      "pFrais": true
    },
    {
      "title": "Marron",
      "pFrais": true
    },
    {
      "title": "Melon",
      "pFrais": true
    },
    {
      "title": "Mirabelle",
      "pFrais": true
    },
    {
      "title": "Myrtille",
      "pFrais": true
    },
    {
      "title": "Navet",
      "pFrais": true
    },
    {
      "title": "Nectarine",
      "pFrais": true
    },
    {
      "title": "Noix de coco",
      "pFrais": true
    },
    {
      "title": "Oignon",
      "pFrais": true
    },
    {
      "title": "Oignon rouge",
      "pFrais": true
    },
    {
      "title": "Olives",
      "pFrais": true
    },
    {
      "title": "Orange",
      "pFrais": true
    },
    {
      "title": "Orange confite",
      "pFrais": true
    },
    {
      "title": "Orange sanguine",
      "pFrais": true
    },
    {
      "title": "Pamplemousse",
      "pFrais": true
    },
    {
      "title": "Panais",
      "pFrais": true
    },
    {
      "title": "Papaye",
      "pFrais": true
    },
    {
      "title": "Pastèque",
      "pFrais": true
    },
    {
      "title": "Petit oignon blanc",
      "pFrais": true
    },
    {
      "title": "Pistaches",
      "pFrais": true
    },
    {
      "title": "Poire",
      "pFrais": true
    },
    {
      "title": "Poireau",
      "pFrais": true
    },
    {
      "title": "Pois mange-tout",
      "pFrais": true
    },
    {
      "title": "Petits pois",
      "pFrais": true
    },
    {
      "title": "Poivron",
      "pFrais": true
    },
    {
      "title": "Poivron (jaune)",
      "pFrais": true
    },
    {
      "title": "Poivron (rouge)",
      "pFrais": true
    },
    {
      "title": "Poivron (vert)",
      "pFrais": true
    },
    {
      "title": "Pomme",
      "pFrais": true
    },
    {
      "title": "Pomme de terre",
      "pFrais": true
    },
    {
      "title": "Potimarron",
      "pFrais": true
    },
    {
      "title": "Potiron",
      "pFrais": true
    },
    {
      "title": "Pousses de soja",
      "alergenesIng": [
        "Soja"
      ],
      "pFrais": true
    },
    {
      "title": "Prune",
      "pFrais": true
    },
    {
      "title": "Pruneau",
      "pFrais": true
    },
    {
      "title": "Quetsche",
      "pFrais": true
    },
    {
      "title": "Radis",
      "pFrais": true
    },
    {
      "title": "Radis long",
      "pFrais": true
    },
    {
      "title": "Raisin",
      "pFrais": true
    },
    {
      "title": "Raisin sec",
      "pFrais": false
    },
    {
      "title": "Rhubarbe",
      "pFrais": true
    },
    {
      "title": "Salade",
      "pFrais": true
    },
    {
      "title": "Salsifis",
      "pFrais": true
    },
    {
      "title": "Tomate",
      "pFrais": true
    },
    {
      "title": "Tomate (conserve)",
      "pFrais": false
    },
    {
      "title": "Tomate séchée",
      "pFrais": false
    },
    {
      "title": "Tomates cerises",
      "pFrais": true
    }
  ]
}